[
  {
      "Nome": "João",
      "Sobrenome": "Silva",
      "Idade": 35,
      "Gênero": "Masculino",
      "Endereço": "Rua das Flores",
      "Número de telefone": "123-456-7890",
      "Email": "joao.silva@email.com",
      "Saldo da conta": 1500.00,
      "Número da conta": "12345",
      "Tipo de conta": "Corrente",
      "Limite de crédito": 2000.00,
      "Data de abertura da conta": "2020-01-15"
  },
  {
      "Nome": "Maria",
      "Sobrenome": "Santos",
      "Idade": 28,
      "Gênero": "Feminino",
      "Endereço": "Avenida Principal",
      "Número de telefone": "987-654-3210",
      "Email": "maria.santos@email.com",
      "Saldo da conta": 2300.50,
      "Número da conta": "54321",
      "Tipo de conta": "Poupança",
      "Limite de crédito": 1000.00,
      "Data de abertura da conta": "2019-05-20"
  },
  {
      "Nome": "Pedro",
      "Sobrenome": "Almeida",
      "Idade": 45,
      "Gênero": "Masculino",
      "Endereço": "Rua do Comércio",
      "Número de telefone": "555-123-7890",
      "Email": "pedro.almeida@email.com",
      "Saldo da conta": 3200.25,
      "Número da conta": "67890",
      "Tipo de conta": "Corrente",
      "Limite de crédito": 3000.00,
      "Data de abertura da conta": "2018-09-10"
  },
  {
      "Nome": "Ana",
      "Sobrenome": "Cardoso",
      "Idade": 22,
      "Gênero": "Feminino",
      "Endereço": "Rua da Praia",
      "Número de telefone": "777-999-3333",
      "Email": "ana.cardoso@email.com",
      "Saldo da conta": 1850.75,
      "Número da conta": "11223",
      "Tipo de conta": "Poupança",
      "Limite de crédito": 500.00,
      "Data de abertura da conta": "2021-03-05"
  },
  {
      "Nome": "Carlos",
      "Sobrenome": "Soares",
      "Idade": 40,
      "Gênero": "Masculino",
      "Endereço": "Alameda dos Parques",
      "Número de telefone": "333-888-2222",
      "Email": "carlos.soares@email.com",
      "Saldo da conta": 4100.20,
      "Número da conta": "33445",
      "Tipo de conta": "Corrente",
      "Limite de crédito": 5000.00,
      "Data de abertura da conta": "2017-07-12"
  },
  {
      "Nome": "Lúcia",
      "Sobrenome": "Fernandes",
      "Idade": 32,
      "Gênero": "Feminino",
      "Endereço": "Avenida Central",
      "Número de telefone": "111-444-7777",
      "Email": "lucia.fernandes@email.com",
      "Saldo da conta": 2750.60,
      "Número da conta": "55667",
      "Tipo de conta": "Corrente",
      "Limite de crédito": 4000.00,
      "Data de abertura da conta": "2016-02-28"
  }
]
